{
    "name": "Barry Lyndon",
    "country": [
        "English",
        "German",
        "French"
    ],
    "language": [
        "    ",
        "See more\u00a0\u00bb",
        "    "
    ],
    "runtime": "    ",
    "genre": [
        "Adventure"
    ],
    "poster": "https://m.media-amazon.com/images/M/MV5BNmY0MWY2NDctZDdmMi00MjA1LTk0ZTQtZDMyZTQ1NTNlYzVjXkEyXkFqcGdeQXVyMjUzOTY1NTc@._V1_UX182_CR0,0,182,268_AL__QL50.jpg",
    "bio": "An Irish rogue wins the heart of a rich widow and assumes her dead husband's aristocratic position in 18th-century England.",
    "director": [
        "Stanley Kubrick"
    ]
}