{
    "name": "T\u00f4ky\u00f4 monogatari",
    "country": [
        "Japanese",
        "English"
    ],
    "language": [
        "    ",
        "See more\u00a0\u00bb",
        "    "
    ],
    "genre": [
        "Drama"
    ],
    "poster": "https://m.media-amazon.com/images/M/MV5BYWQ4ZTRiODktNjAzZC00Nzg1LTk1YWQtNDFmNDI0NmZiNGIwXkEyXkFqcGdeQXVyNzkwMjQ5NzM@._V1_UY268_CR2,0,182,268_AL__QL50.jpg",
    "bio": "An old couple visit their children and grandchildren in the city, but receive little attention.",
    "director": [
        "Yasujir\u00f4 Ozu"
    ]
}