{
    "name": "Mononoke-hime",
    "country": [
        "Japan",
        "USA"
    ],
    "language": [
        "Japanese"
    ],
    "runtime": "Dolby Digital",
    "genre": [
        "Animation"
    ],
    "poster": "https://m.media-amazon.com/images/M/MV5BNGIzY2IzODQtNThmMi00ZDE4LWI5YzAtNzNlZTM1ZjYyYjUyXkEyXkFqcGdeQXVyODEzNjM5OTQ@._V1_UX182_CR0,0,182,268_AL__QL50.jpg",
    "bio": "On a journey to find the cure for a Tatarigami's curse, Ashitaka finds himself in the middle of a war between the forest gods and Tatara, a mining colony. In this quest he also meets San, the Mononoke Hime.",
    "director": [
        "Hayao Miyazaki"
    ]
}